{
  "Zeenou": {
    "name": "Zeenou",
    "nameRus": "Зиноу",
    "health": 3500,                
    "damage": 300,
    "cost": 100,
    "costType": "star",
    "url": "https://i.ibb.co/rfwtrXY/Zeenou.jpg",
    "path": "./images/heroes/Zeenou.jpg",
    "available": "Да",
    "vip": false,
    "upgradeCost": 65,
    "type": "common",
    "elements": ["water"]
  },
  "Dilan": {
    "name": "Dilan",
    "nameRus": "Дилан",
    "health": 5000,
    "damage": 50,
    "cost": 250,
    "costType": "star",
    "url": "https://i.ibb.co/1b9C0vg/Dilan.jpg",
    "path": "./images/heroes/Dilan.jpg",
    "available": "Да",
    "vip": false,
    "upgradeCost": 80,
    "type": "common",
    "elements": ["fire"]
  },
  "Darius": {
    "name": "Darius",
    "nameRus": "Дариус",
    "health": 25000,
    "damage": 750,
    "cost": "Не известна.",
    "costType": "dev",
    "url": "https://i.ibb.co/dBhCCGS/Darius.jpg",
    "path": "./images/heroes/Darius.jpg",
    "available": "Под",
    "vip": false,
    "upgradeCost": 100,
    "type": "private",
    "elements": ["legendary", "gold"]
  },
  "Selena": {
    "name": "Selena",
    "nameRus": "Селена",
    "health": 7000,
    "damage": 500,
    "cost": 50,
    "costType": "crystal",
    "url": "https://i.ibb.co/KNP5tC1/Selena.jpg",
    "path": "./images/heroes/Selena.jpg",
    "available": "Да",
    "vip": false,
    "upgradeCost": 120,
    "type": "common",
    "elements": ["magic", "fire"]
  },
  "Cthulhu": {
    "name": "Cthulhu",
    "nameRus": "Ктулху",
    "health": 8000,
    "damage": 650,
    "cost": 200,
    "costType": "crystal",
    "url": "https://i.ibb.co/FzPgCFW/Cthulhu.jpg",
    "path": "./images/heroes/Cthulhu.jpg",
    "available": "Да",
    "vip": false,
    "upgradeCost": 140,
    "type": "elite",
    "elements": ["water", "nature"]
  },
  "Zeus": {
    "name": "Zeus",
    "nameRus": "Зевс",
    "health": 25000,
    "damage": 2500,
    "cost": 1500,
    "costType": "crystal",
    "url": "https://i.ibb.co/RQLbCGr/Zeus.jpg",
    "path": "./images/heroes/Zeus.jpg",
    "available": "Да",
    "vip": false,
    "upgradeCost": 95,
    "type": "private",
    "elements": ["legendary", "light"]
  },
  "Perfect-duo": {
    "name": "Perfect-duo",
    "nameRus": "Идеальный Дуэт",
    "health": 10000,
    "damage": 800,
    "cost": 200,
    "costType": "crystal",
    "url": "https://i.ibb.co/YRQ0m7L/Perfect-Duo.jpg",
    "path": "./images/heroes/Perfect-Duo.jpg",
    "available": "Да",
    "vip": true,
    "upgradeCost": 130,
    "type": "elite",
    "elements": ["nature", "land"]
  },
  "Eragon": {
    "name": "Eragon",
    "nameRus": "Эрагон",
    "health": 44000,
    "damage": 6000,
    "cost": 1000,
    "costType": "crystal",
    "url": "https://i.ibb.co/frb1BsG/Eragon.jpg",
    "path": "./images/heroes/Eragon.jpg",
    "available": "Да",
    "vip": true,
    "marry": true,
    "upgradeCost": 400,
    "type": "mythical",
    "elements": ["light", "magic"]
  },
  "Ariel": {
    "name": "Ariel",
    "nameRus": "Ариэль",
    "health": 11000,
    "damage": 1000,
    "cost": 500,
    "costType": "crystal",
    "url": "https://i.ibb.co/xY0NnFn/Ariel.jpg",
    "path": "./images/heroes/Ariel.jpg",
    "available": "Да",
    "vip": true,
    "upgradeCost": 140,
    "type": "furious",
    "elements": ["nature"]
  },
  "Archangel": {
    "name": "Archangel",
    "nameRus": "Архангел",
    "health": 6000,
    "damage": 450,
    "cost": 50,
    "costType": "crystal",
    "url": "https://i.ibb.co/xJSTDWp/Archangel.jpg",
    "path": "./images/heroes/Archangel.jpg",
    "available": "Да",
    "vip": false,
    "upgradeCost": 45,
    "type": "common",
    "elements": ["light"]
  },
  "Darkangel": {
    "name": "Darkangel",
    "nameRus": "Даркангел",
    "health": 13000,
    "damage": 900,
    "cost": 500,
    "costType": "crystal",
    "url": "https://i.ibb.co/YRjMgkF/Darkangel.jpg",
    "path": "./images/heroes/Darkangel.jpg",
    "available": "Да",
    "vip": false,
    "upgradeCost": 200,
    "type": "furious",
    "elements": ["land", "fire"]
  },
  "Kumbhakarna": {
    "name": "Kumbhakarna",
    "nameRus": "Кумбхакарна",
    "health": 6000,
    "damage": 450,
    "cost": 200,
    "costType": "crystal",
    "url": "https://i.ibb.co/Bs6V3Bz/Kumbhakarna.png",
    "path": "./images/heroes/Kumbhakarna.png",
    "available": "Да",
    "vip": false,
    "upgradeCost": 65,
    "type": "elite",
    "elements": ["fire", "nature"]
  },
  "Atalanta": {
    "name": "Atalanta",
    "nameRus": "Аталанта",
    "health": 15000,
    "damage": 950,
    "cost": 200,
    "costType": "crystal",
    "url": "https://i.ibb.co/XFCSCQm/Atalanta.png",
    "path": "./images/heroes/Atalanta.png",
    "available": "Да",
    "vip": false,
    "upgradeCost": 300,
    "type": "elite",
    "elements": ["light", "magic"]
  },
  "Athena": {
    "name": "Athena",
    "nameRus": "Афина",
    "health": 15000,
    "damage": 1300,
    "cost": 500,
    "costType": "crystal",
    "url": "https://i.ibb.co/LvKLWT1/Countess.png",
    "path": "./images/heroes/Athena.png",
    "available": "Да",
    "vip": true,
    "upgradeCost": 450,
    "type": "furious",
    "elements": ["magic", "light"]
  },
  "Blazer": {
    "name": "Blazer",
    "nameRus": "Блейзер",
    "health": 16000,
    "damage": 1600,
    "cost": 500,
    "costType": "crystal",
    "url": "https://i.ibb.co/QJ6BvD3/Blazer.png",
    "path": "./images/heroes/Blazer.png",
    "available": "Да",
    "vip": true,
    "upgradeCost": 550,
    "type": "furious",
    "elements": ["fire", "fire"]
  },
  "Snake-woman": {
    "name": "Snake-woman",
    "nameRus": "Женщина-змея",
    "health": 6500,
    "damage": 600,
    "cost": 50,
    "costType": "crystal",
    "url": "https://i.ibb.co/7RfSRjM/Snakewoman.jpg",
    "path": "./images/heroes/Snakewoman.jpg",
    "available": "Да",
    "vip": false,
    "upgradeCost": 60,
    "type": "common",
    "elements": ["nature", "magic"]
  },
  "Mistress-forest": {
    "name": "Mistress-forest",
    "nameRus": "Повелительница леса",
    "health": 5500,
    "damage": 570,
    "cost": 50,
    "costType": "crystal",
    "url": "https://i.ibb.co/8Njqg9z/Mistress-Forest.jpg",
    "path": "./images/heroes/Mistress-Forest.jpg",
    "available": "Да",
    "vip": false,
    "upgradeCost": 55,
    "type": "common",
    "elements": ["nature", "nature"]
  },
  "Hunter": {
    "name": "Hunter",
    "nameRus": "Охотник",
    "health": 20000,
    "damage": 2050,
    "cost": 1000,
    "costType": "crystal",
    "url": "https://i.ibb.co/8MmXtmS/Hunter.jpg",
    "path": "./images/heroes/Hunter.jpg",
    "available": "Да",
    "vip": true,
    "upgradeCost": 500,
    "type": "mythical",
    "elements": ["magic", "nature"]
  },
  "Broken": {
    "name": "Broken",
    "nameRus": "Разбитый",
    "health": 55000,
    "damage": 5500,
    "cost": "Не известна.",
    "costType": "dev",
    "url": "https://i.ibb.co/9twZbPm/Broken.jpg",
    "path": "./images/heroes/Broken.jpg",
    "available": "Под",
    "vip": false,
    "upgradeCost": 300,
    "type": "private",
    "elements": ["legendary", "land"]
  },
  "Horus": {
    "name": "Horus",
    "nameRus": "Горус",
    "health": 8000,
    "damage": 770,
    "cost": "Не известна.",
    "costType": "dev",
    "url": "https://i.ibb.co/0M3h3Pr/Horus.jpg",
    "path": "./images/heroes/Horus.jpg",
    "available": "Под",
    "vip": false,
    "upgradeCost": 75,
    "type": "elite",
    "elements": ["gold", "magic"]
  },
  "Thoth-amon": {
    "name": "Thoth-amon",
    "nameRus": "Тот-амон",
    "health": 10600,
    "damage": 990,
    "cost": "Не известна.",
    "costType": "dev",
    "url": "https://i.ibb.co/8jZMfSz/Thoth-Amon.jpg",
    "path": "./images/heroes/Thoth-Amon.jpg",
    "available": "Под",
    "vip": false,
    "upgradeCost": 105,
    "type": "elite",
    "elements": ["gold", "magic"]
  },
  "Anubis": {
    "name": "Anubis",
    "nameRus": "Анубис",
    "health": 17000,
    "damage": 1300,
    "cost": "Не известна.",
    "costType": "dev",
    "url": "https://i.ibb.co/R2fB8zm/Anubis.jpg",
    "path": "./images/heroes/Anubis.jpg",
    "available": "Под",
    "vip": false,
    "upgradeCost": 350,
    "type": "furious",
    "elements": ["gold", "magic"]
  },
  "Sebek": {
    "name": "Sebek",
    "nameRus": "Себек",
    "health": 25000,
    "damage": 1650,
    "cost": "Не известна.",
    "costType": "dev",
    "url": "https://i.ibb.co/R4TNRd0/Sebek.jpg",
    "path": "./images/heroes/Sebek.jpg",
    "available": "Под",
    "vip": false,
    "upgradeCost": 405,
    "type": "furious",
    "elements": ["gold", "magic"]
  },
  "Hathor": {
    "name": "Hathor",
    "nameRus": "Хатхор",
    "health": 35000,
    "damage": 1970,
    "cost": "Не известна.",
    "costType": "dev",
    "url": "https://i.ibb.co/j6R4073/Hathor.jpg",
    "path": "./images/heroes/Hathor.jpg",
    "available": "Под",
    "vip": true,
    "upgradeCost": 600,
    "type": "mythical",
    "elements": ["gold", "magic"]
  },
  "Supernatural-ramses": {
    "name": "Supernatural-ramses",
    "nameRus": "Сверхъестественный Рамсес",
    "health": 50000,
    "damage": 2500,
    "cost": "Не известна.",
    "costType": "dev",
    "url": "https://i.ibb.co/yNb3dCq/Supernatural-Ramses.jpg",
    "path": "./images/heroes/Supernatural-Ramses.jpg",
    "available": "Под",
    "vip": true,
    "upgradeCost": 750,
    "type": "mythical",
    "elements": ["gold", "magic"]
  },
  "Zero": {
    "name": "Zero",
    "nameRus": "Зеро",
    "health": 100000,
    "damage": 6000,
    "cost": 1000,
    "costType": "crystal",
    "url": "https://i.ibb.co/ZzGxvbL/Zero.jpg",
    "path": "./images/heroes/Zero.jpg",
    "available": "Да",
    "vip": false,
    "upgradeCost": 1500,
    "type": "mythical",
    "elements": ["magic", "light"]
  },
  "Toothless": {
    "name": "Toothless",
    "nameRus": "Беззубик",
    "health": 700000,
    "damage": 20000,
    "cost": 1900,
    "costType": "crystal",
    "url": "https://i.ibb.co/kqrnSWH/Toothless.png",
    "path": "./images/heroes/Toothless.png",
    "available": "Да",
    "vip": false,
    "upgradeCost": 1000,
    "type": "private",
    "elements": ["legendary", "magic"]
  },
  "X": {
    "name": "X",
    "nameRus": "Х",
    "health": 155000,
    "damage": 7500,
    "cost": 1000,
    "costType": "crystal",
    "url": "https://i.ibb.co/54hGTN4/X.jpg",
    "path": "./images/heroes/X.jpg",
    "available": "Да",
    "vip": true,
    "upgradeCost": 1800,
    "type": "mythical",
    "elements": ["light", "magic"]
  },
  "Ancalgon": {
    "name": "Ancalgon",
    "nameRus": "Анкалгон",
    "health": 300000,
    "damage": 15000,
    "cost": 1000,
    "costType": "crystal",
    "url": "https://i.ibb.co/31Dh300/Ancalgon.jpg",
    "path": "./images/heroes/Ancalgon.jpg",
    "available": "Да",
    "vip": true,
    "upgradeCost": 3000,
    "type": "mythical",
    "elements": ["magic", "land"]
  },
  "Tartarus": {
    "name": "Tartarus",
    "nameRus": "Тартарус",
    "health": 160000,
    "damage": 11000,
    "cost": 1500,
    "costType": "crystal",
    "url": "https://i.ibb.co/6WfMD3v/Tartarus.jpg",
    "path": "./images/heroes/Tartarus.jpg",
    "available": "Да",
    "vip": false,
    "upgradeCost": 1000,
    "type": "private",
    "elements": ["legendary", "light"]
  },
  "Hookfang": {
    "name": "Hookfang",
    "nameRus": "Кривоклык",
    "health": 17000,
    "damage": 5000,
    "cost": 500,
    "costType": "crystal",
    "url": "https://i.ibb.co/9VRrJqV/Hookfang.jpg",
    "path": "./images/heroes/Hookfang.jpg",
    "available": "Да",
    "vip": false,
    "upgradeCost": 600,
    "type": "furious",
    "elements": ["fire", "nature"]
  },
  "Koko": {
    "name": "Koko",
    "nameRus": "Коко",
    "health": 7500,
    "damage": 450,
    "cost": 200,
    "costType": "crystal",
    "url": "https://i.ibb.co/cDsTXNv/Koko.jpg",
    "path": "./images/heroes/Koko.jpg",
    "available": "Да",
    "vip": false,
    "upgradeCost": 200,
    "type": "elite",
    "elements": ["water", "water"]
  },
  "Dido": {
    "name": "Dido",
    "nameRus": "Дидо",
    "health": 20000,
    "damage": 900,
    "cost": 500,
    "costType": "crystal",
    "url": "https://i.ibb.co/VCBmgX0/Dido.jpg",
    "path": "./images/heroes/Dido.jpg",
    "available": "Да",
    "vip": false,
    "upgradeCost": 540,
    "type": "furious",
    "elements": ["magic", "water"]
  },
  "Light": {
    "name": "Light",
    "nameRus": "Свет",
    "health": 190000,
    "damage": 8500,
    "cost": 1000,
    "costType": "crystal",
    "url": "https://i.ibb.co/d6cLWMD/Light.jpg",
    "path": "./images/heroes/Light.jpg",
    "available": "Да",
    "vip": false,
    "upgradeCost": 2000,
    "type": "mythical",
    "elements": ["light", "magic"]
  },
  "Tyrus": {
    "name": "Tyrus",
    "nameRus": "Тайрус",
    "health": 930000,
    "damage": 10500,
    "cost": 1750,
    "costType": "crystal",
    "url": "https://i.ibb.co/186FnQ8/Tyrus.jpg",
    "path": "./images/heroes/Tyrus.jpg",
    "available": "Да",
    "vip": false,
    "upgradeCost": 1000,
    "type": "private",
    "elements": ["legendary", "nature"]
  },
  "Girl": {
    "name": "Girl",
    "nameRus": "Девушка",
    "health": 120000,
    "damage": 7900,
    "cost": 0,
    "costType": "star",
    "url": "https://i.ibb.co/BG6pWzh/Girl.jpg",
    "path": "./images/heroes/Girl.jpg",
    "available": "Да",
    "vip": false,
    "upgradeCost": 1000,
    "type": "private",
    "subLevel": 2,
    "elements": ["legendary", "magic"]
  },
  "Shadow": {
    "name": "Shadow",
    "nameRus": "Тень",
    "health": 145000,
    "damage": 9500,
    "cost": 1000,
    "costType": "crystal",
    "url": "https://i.ibb.co/WPMm18b/Shadow.jpg",
    "path": "./images/heroes/Shadow.jpg",
    "available": "Да",
    "vip": false,
    "upgradeCost": 1000,
    "type": "private",
    "subLevel": 2,
    "elements": ["legendary", "magic"]
  },
  "Clarity": {
    "name": "Clarity",
    "nameRus": "Ясность",
    "health": 180000,
    "damage": 11000,
    "cost": 0,
    "costType": "star",
    "url": "https://i.ibb.co/pdVtBrZ/Clarity.jpg",
    "path": "./images/heroes/Clarity.jpg",
    "available": "Да",
    "vip": false,
    "upgradeCost": 1000,
    "type": "private",
    "subLevel": 3,
    "elements": ["legendary", "light"]
  },
  "Red": {
    "name": "Red",
    "nameRus": "Ред",
    "health": 46000,
    "damage": 4000,
    "cost": 0,
    "costType": "star",
    "url": "https://i.ibb.co/nbkqtLQ/Red.jpg",
    "path": "./images/heroes/Red.jpg",
    "available": "Да",
    "vip": false,
    "upgradeCost": 700,
    "type": "mythical",
    "subLevel": 1,
    "elements": ["fire", "magic"]
  },
  "Alfonso": {
    "name": "Alfonso",
    "nameRus": "Альфонсо",
    "health": 110000,
    "damage": 8000,
    "cost": "Не известна.",
    "costType": "dev",
    "url": "https://i.ibb.co/9w4wFYq/Alfonso.jpg",
    "path": "./images/heroes/Alfonso.jpg",
    "available": "loc",
    "vip": false,
    "upgradeCost": 833,
    "type": "mythical",
    "elements": ["magic", "gold"]
  },
  "Gigantes": {
    "name": "Gigantes",
    "nameRus": "Гигантес",
    "health": 450000,
    "damage": 20000,
    "cost": 1500,
    "costType": "crystal",
    "url": "https://i.ibb.co/dKY8sVG/Gigantos.jpg",
    "path": "./images/heroes/Gigantos.jpg",
    "available": "Да",
    "vip": false,
    "upgradeCost": 1050,
    "type": "private",
    "elements": ["legendary", "gold"]
  },
  "Dranna": {
    "name": "Dranna",
    "nameRus": "Дранна",
    "health": 45000,
    "damage": 980,
    "cost": 500,
    "costType": "crystal",
    "url": "https://i.ibb.co/h9yL5bf/Dranna.jpg",
    "path": "./images/heroes/Dranna.jpg",
    "available": "Да",
    "vip": false,
    "upgradeCost": 655,
    "type": "furious",
    "elements": ["water", "magic"]
  },
  "Kindness": {
    "name": "Kindness",
    "nameRus": "Доброта",
    "health": 60000,
    "damage": 1175,
    "cost": 500,
    "costType": "crystal",
    "url": "https://i.ibb.co/XLsXStQ/Kindness.jpg",
    "path": "./images/heroes/Kindness.jpg",
    "available": "Да",
    "vip": false,
    "upgradeCost": 700,
    "type": "furious",
    "elements": ["magic", "light"]
  },
  "Merlin": {
    "name": "Merlin",
    "nameRus": "Мерлин",
    "health": 75000,
    "damage": 1350,
    "cost": 500,
    "costType": "crystal",
    "url": "https://i.ibb.co/xMJWzFM/Merlin.jpg",
    "path": "./images/heroes/Merlin.jpg",
    "available": "Да",
    "vip": true,
    "upgradeCost": 756,
    "type": "furious",
    "elements": ["water", "fire"]
  },
  "Lyric": {
    "name": "Lyric",
    "nameRus": "Лирика",
    "health": 366000,
    "damage": 15000,
    "cost": 1000,
    "costType": "crystal",
    "url": "https://i.ibb.co/9G1gD00/Lyric.jpg",
    "path": "./images/heroes/Lyric.jpg",
    "available": "Да",
    "vip": false,
    "upgradeCost": 3333,
    "type": "mythical",
    "elements": ["magic", "light"]
  },
  "Muratova": {
    "name": "Muratova",
    "nameRus": "Муратова",
    "health": 610000,
    "damage": 17500,
    "cost": 1750,
    "costType": "crystal",
    "url": "https://i.ibb.co/93tRQdS/Muratova.jpg",
    "path": "./images/heroes/Muratova.jpg",
    "available": "Да",
    "vip": false,
    "upgradeCost": 1000,
    "type": "private",
    "elements": ["legendary", "light"]
  },
  "Centurion": {
    "name": "Centurion",
    "nameRus": "Центурион",
    "health": 66000,
    "damage": 33500,
    "cost": 1000,
    "costType": "crystal",
    "url": "https://i.ibb.co/Zd8q63S/Centurion.jpg",
    "path": "./images/heroes/Centurion.jpg",
    "available": "Да",
    "vip": false,
    "upgradeCost": 963,
    "type": "mythical",
    "elements": ["fire", "nature"]
  },
  "Mummy": {
    "name": "Mummy",
    "nameRus": "Мумия",
    "health": 18000,
    "damage": 800,
    "cost": "Не известна.",
    "costType": "hal",
    "url": "https://i.ibb.co/hdMd8Gp/Mummy.jpg",
    "path": "./images/heroes/Mummy.jpg",
    "available": "пак",
    "vip": false,
    "upgradeCost": 230,
    "type": "elite",
    "elements": ["magic", "fire"]
  },
  "Plague-doctor": {
    "name": "Plague-doctor",
    "nameRus": "Чумной-доктор",
    "health": 27000,
    "damage": 1500,
    "cost": "Не известна.",
    "costType": "hal",
    "url": "https://i.ibb.co/DR2Z5kx/Plague-doctor.jpg",
    "path": "./images/heroes/Plague-doctor.jpg",
    "available": "пак",
    "vip": false,
    "upgradeCost": 450,
    "type": "furious",
    "elements": ["magic", "magic"]
  },
  "Secret": {
    "name": "Secret",
    "nameRus": "Тайна",
    "health": 44000,
    "damage": 1250,
    "cost": "Не известна.",
    "costType": "hal",
    "url": "https://i.ibb.co/TBn8qYX/Secret.jpg",
    "path": "./images/heroes/Secret.jpg",
    "available": "пак",
    "vip": false,
    "upgradeCost": 555,
    "type": "furious",
    "elements": ["magic", "nature"]
  },
  "Witch": {
    "name": "Witch",
    "nameRus": "Ведьма",
    "health": 166000,
    "damage": 8650,
    "cost": "Не известна.",
    "costType": "hal",
    "url": "https://i.ibb.co/wLLrbRp/Witch.jpg",
    "path": "./images/heroes/Witch.jpg",
    "available": "пак",
    "vip": false,
    "upgradeCost": 855,
    "type": "mythical",
    "elements": ["magic", "gold"]
  },
  "Horseman": {
    "name": "Horseman",
    "nameRus": "Всадник",
    "health": 360000,
    "damage": 9950,
    "cost": 800,
    "costType": "crystal",
    "url": "https://i.ibb.co/yYh4C4s/Horseman.jpg",
    "path": "./images/heroes/Horseman.jpg",
    "available": "Да",
    "vip": false,
    "upgradeCost": 1000,
    "type": "private",
    "elements": ["legendary", "fire"]
  },
  "Muratov": {
    "name": "Muratov",
    "nameRus": "Муратов",
    "health": 244000,
    "damage": 6550,
    "cost": 1000,
    "costType": "crystal",
    "url": "https://i.ibb.co/fSYmxH2/Muratov.jpg",
    "path": "./images/heroes/Muratov.jpg",
    "available": "Да",
    "vip": false,
    "upgradeCost": 1200,
    "type": "mythical",
    "elements": ["light", "land"]
  },
  "Golden": {
    "name": "Golden",
    "nameRus": "Золотой",
    "health": 644000,
    "damage": 8500,
    "cost": "Не известна.",
    "costType": "dev",
    "url": "https://i.ibb.co/JRfhFPZ/Golden.jpg",
    "path": "./images/heroes/Golden.jpg",
    "available": "Под",
    "vip": false,
    "upgradeCost": 1000,
    "type": "private",
    "elements": ["legendary", "gold"]
  },
  "Humanoid": {
    "name": "Humanoid",
    "nameRus": "Гуманоид",
    "health": 500000,
    "damage": 10000,
    "cost": 1500,
    "costType": "crystal",
    "url": "https://i.ibb.co/2cQqBzj/Humanoid.jpg",
    "path": "./images/heroes/Humanoid.jpg",
    "available": "Да",
    "vip": false,
    "upgradeCost": 1000,
    "type": "private",
    "elements": ["legendary", "land"]
  },
  "Hella": {
    "name": "Hella",
    "nameRus": "Хелла",
    "health": 500000,
    "damage": 10000,
    "cost": 1500,
    "costType": "crystal",
    "url": "https://i.ibb.co/TwsFspk/Hella.jpg",
    "path": "./images/heroes/Hella.jpg",
    "available": "Да",
    "vip": false,
    "upgradeCost": 1000,
    "type": "private",
    "elements": ["legendary", "magic"]
  },
  "Skeletron": {
    "name": "Skeletron",
    "nameRus": "Скелетрон",
    "health": 500000,
    "damage": 10000,
    "cost": 1500,
    "costType": "crystal",
    "url": "https://i.ibb.co/cxHbK4t/Skeletron.jpg",
    "path": "./images/heroes/Skeletron.jpg",
    "available": "Да",
    "vip": false,
    "upgradeCost": 1000,
    "type": "private",
    "elements": ["legendary", "magic"]
  },
  "Heavenly": {
    "name": "Heavenly",
    "nameRus": "Небесный",
    "health": 500000,
    "damage": 10000,
    "cost": 1500,
    "costType": "crystal",
    "url": "https://i.ibb.co/3v0cVvG/Heavenly.jpg",
    "path": "./images/heroes/Heavenly.jpg",
    "available": "Да",
    "vip": false,
    "upgradeCost": 1000,
    "type": "private",
    "elements": ["legendary", "light"]
  },
  "Stranger": {
    "name": "Stranger",
    "nameRus": "Чужой",
    "health": 500000,
    "damage": 10000,
    "cost": "Не известна.",
    "costType": "dev",
    "url": "https://i.ibb.co/KhHPYdP/Stranger.jpg",
    "path": "./images/heroes/Stranger.jpg",
    "available": "Под",
    "vip": false,
    "upgradeCost": 1000,
    "type": "private",
    "elements": ["legendary", "fire"]
  },
  "Underman": {
    "name": "Underman",
    "nameRus": "Андермен",
    "health": 500000,
    "damage": 10000,
    "cost": 1500,
    "costType": "crystal",
    "url": "https://i.ibb.co/3T4wD2g/Underman.jpg",
    "path": "./images/heroes/Underman.jpg",
    "available": "Да",
    "vip": true,
    "upgradeCost": 1000,
    "type": "private",
    "elements": ["legendary", "magic"]
  },
  "Noctum": {
    "name": "Noctum",
    "nameRus": "Ноктум",
    "health": 500000,
    "damage": 10000,
    "cost": 1500,
    "costType": "crystal",
    "url": "https://i.ibb.co/bbVQBpC/Noctum.jpg",
    "path": "./images/heroes/Noctum.jpg",
    "available": "Да",
    "vip": true,
    "upgradeCost": 1000,
    "type": "private",
    "elements": ["legendary", "fire"]
  },
  "Lebas": {
    "name": "Lebas",
    "nameRus": "Лебас",
    "health": 500000,
    "damage": 10000,
    "cost": 1500,
    "costType": "crystal",
    "url": "https://i.ibb.co/9yyz3Bh/Lebas.jpg",
    "path": "./images/heroes/Lebas.jpg",
    "available": "Да",
    "vip": true,
    "upgradeCost": 1000,
    "type": "private",
    "elements": ["legendary", "fire"]
  },
  "Venom": {
    "name": "Venom",
    "nameRus": "Веном",
    "health": 500000,
    "damage": 10000,
    "cost": "Не известна.",
    "costType": "dev",
    "url": "https://i.ibb.co/g748Y5V/Venom.jpg",
    "path": "./images/heroes/Venom.jpg",
    "available": "Под",
    "vip": false,
    "upgradeCost": 1000,
    "type": "private",
    "elements": ["legendary", "gold"]
  },
  "Golem": {
    "name": "Golem",
    "nameRus": "Голем",
    "health": 8000,
    "damage": 400,
    "cost": 50,
    "costType": "crystal",
    "url": "https://i.ibb.co/GRNLb0j/Golem.jpg",
    "path": "./images/heroes/Golem.jpg",
    "available": "Да",
    "vip": false,
    "upgradeCost": 100,
    "type": "common",
    "elements": ["land"]
  },
  "Gladiator": {
    "name": "Gladiator",
    "nameRus": "Гладиатор",
    "health": 15000,
    "damage": 1300,
    "cost": 200,
    "costType": "crystal",
    "url": "https://i.ibb.co/jRyZQP2/Gladiator.jpg",
    "path": "./images/heroes/Gladiator.jpg",
    "available": "Да",
    "vip": false,
    "upgradeCost": 300,
    "type": "elite",
    "elements": ["land", "fire"]
  },
  "Plasma": {
    "name": "Plasma",
    "nameRus": "Плазма",
    "health": 50000,
    "damage": 2000,
    "cost": 500,
    "costType": "crystal",
    "url": "https://i.ibb.co/k5JXWjh/Plasma.jpg",
    "path": "./images/heroes/Plasma.jpg",
    "available": "Да",
    "vip": false,
    "upgradeCost": 500,
    "type": "furious",
    "elements": ["land", "light"]
  },
  "Electro": {
    "name": "Electro",
    "nameRus": "Электро",
    "health": 200000,
    "damage": 6000,
    "cost": 1000,
    "costType": "crystal",
    "url": "https://i.ibb.co/VChTsMW/Electro.jpg",
    "path": "./images/heroes/Electro.jpg",
    "available": "Да",
    "vip": true,
    "upgradeCost": 750,
    "type": "mythical",
    "elements": ["light", "land"]
  },
  "Monster-zero": {
    "name": "Monster-zero",
    "nameRus": "Монстр-зеро",
    "health": 500000,
    "damage": 10000,
    "cost": 1500,
    "costType": "crystal",
    "url": "https://i.ibb.co/NnhGdBh/Monster-zero.jpg",
    "path": "./images/heroes/Monster-zero.jpg",
    "available": "Да",
    "vip": true,
    "upgradeCost": 1000,
    "type": "private",
    "elements": ["legendary", "magic"]
  },
  "Alena": {
    "name": "Alena",
    "nameRus": "Алэна",
    "health": 500000,
    "damage": 10000,
    "cost": 1500,
    "costType": "crystal",
    "url": "https://i.ibb.co/0yc7Jy2/Alena.jpg",
    "path": "./images/heroes/Alena.jpg",
    "available": "Да",
    "vip": true,
    "upgradeCost": 1000,
    "type": "private",
    "elements": ["legendary", "land"],
    "blockBreeding": true
  },
  "Volcano": {
    "name": "Volcano",
    "nameRus": "Вулкан",
    "health": 750000,
    "damage": 15000,
    "cost": "Не известна.",
    "costType": "dev",
    "url": "https://i.ibb.co/PzzCRrq/Volcano.jpg",
    "path": "./images/heroes/Volcano.jpg",
    "available": "Под",
    "vip": true,
    "upgradeCost": 1000,
    "type": "private",
    "elements": ["legendary", "land"],
    "blockBreeding": true
  },
  "Tricky": {
    "name": "Tricky",
    "nameRus": "Хитрая",
    "health": 500000,
    "damage": 10000,
    "cost": 1500,
    "costType": "crystal",
    "url": "https://i.ibb.co/3m9HNth/Tricky.jpg",
    "path": "./images/heroes/Tricky.jpg",
    "available": "Да",
    "vip": true,
    "upgradeCost": 1000,
    "type": "private",
    "elements": ["legendary", "nature"]
  },
  "Sleepy": {
    "name": "Sleepy",
    "nameRus": "Сонный",
    "health": 500000,
    "damage": 10000,
    "cost": 1500,
    "costType": "crystal",
    "url": "https://i.ibb.co/HgT99hY/Sleepy.jpg",
    "path": "./images/heroes/Sleepy.jpg",
    "available": "Да",
    "vip": true,
    "upgradeCost": 1000,
    "type": "private",
    "elements": ["legendary", "land"]
  },
  "Arun": {
    "name": "Arun",
    "nameRus": "Арун",
    "health": 500000,
    "damage": 10000,
    "cost": 1500,
    "costType": "crystal",
    "url": "https://i.ibb.co/KKx89yM/Arun.jpg",
    "path": "./images/heroes/Arun.jpg",
    "available": "Да",
    "vip": false,
    "upgradeCost": 1000,
    "type": "private",
    "elements": ["legendary", "water"]
  },
  "Montra": {
    "name": "Montra",
    "nameRus": "Монтра",
    "health": 500000,
    "damage": 10000,
    "cost": 1500,
    "costType": "crystal",
    "url": "https://i.ibb.co/160rC1t/Montra.jpg",
    "path": "./images/heroes/Montra.jpg",
    "available": "Да",
    "vip": false,
    "upgradeCost": 1000,
    "type": "private",
    "elements": ["legendary", "water"],
    "blockBreeding": true
  },
  "Poseidon": {
    "name": "Poseidon",
    "nameRus": "Посейдон",
    "health": 1000000,
    "damage": 30000,
    "cost": 2600,
    "costType": "crystal",
    "url": "https://i.ibb.co/WPtDc3Q/Poseidon.jpg",
    "path": "./images/heroes/Poseidon.jpg",
    "available": "Да",
    "vip": true,
    "upgradeCost": 1000,
    "type": "private",
    "elements": ["legendary", "water"],
    "blockBreeding": true
  },
  "Leonard": {
    "name": "Leonard",
    "nameRus": "Леонард",
    "health": 200000,
    "damage": 6000,
    "cost": 1000,
    "costType": "crystal",
    "url": "https://i.ibb.co/zRDmgK0/Leonard.jpg",
    "path": "./images/heroes/Leonard.jpg",
    "available": "Да",
    "vip": true,
    "upgradeCost": 750,
    "type": "mythical",
    "elements": ["water", "land"],
    "blockBreeding": true
  },
  "Overlord": {
    "name": "Overlord",
    "nameRus": "Владыка",
    "health": 1000000,
    "damage": 30000,
    "cost": 2600,
    "costType": "crystal",
    "url": "https://i.ibb.co/G0rt4N0/Overlord.jpg",
    "path": "./images/heroes/Overlord.jpg",
    "available": "Да",
    "vip": true,
    "upgradeCost": 1000,
    "type": "private",
    "elements": ["legendary", "magic"],
    "blockBreeding": true
  },
  "Thanos": {
    "name": "Thanos",
    "nameRus": "Танос",
    "health": 700000,
    "damage": 11000,
    "cost": 2300,
    "costType": "crystal",
    "url": "https://i.ibb.co/G2yywy3/Thanos.jpg",
    "path": "./images/heroes/Thanos.jpg",
    "available": "Да",
    "vip": true,
    "upgradeCost": 1000,
    "type": "private",
    "elements": ["legendary", "land"]
  },
  "Carnage": {
    "name": "Carnage",
    "nameRus": "Карнаж",
    "health": 780000,
    "damage": 12600,
    "cost": 2400,
    "costType": "crystal",
    "url": "https://i.ibb.co/4W4RqPr/Carnage.jpg",
    "path": "./images/heroes/Carnage.jpg",
    "available": "Да",
    "vip": true,
    "upgradeCost": 1000,
    "type": "private",
    "elements": ["legendary", "light"]
  },
  "Surtur": {
    "name": "Surtur",
    "nameRus": "Суртур",
    "health": 950000,
    "damage": 18000,
    "cost": 2450,
    "costType": "crystal",
    "url": "https://i.ibb.co/M795GCC/Surtur.jpg",
    "path": "./images/heroes/Surtur.jpg",
    "available": "Да",
    "vip": true,
    "upgradeCost": 1000,
    "type": "private",
    "elements": ["legendary", "fire"],
    "blockBreeding": true
  },
  "Galactus": {
    "name": "Galactus",
    "nameRus": "Галактус",
    "health": 1000000,
    "damage": 25000,
    "cost": 2550,
    "costType": "crystal",
    "url": "https://i.ibb.co/f8HbC9T/Galactus.jpg",
    "path": "./images/heroes/Galactus.jpg",
    "available": "Да",
    "vip": true,
    "upgradeCost": 1000,
    "type": "private",
    "elements": ["legendary", "magic"],
    "blockBreeding": true
  },
  "Ghost-rider": {
    "name": "Ghost-rider",
    "nameRus": "Призрачный-гонщик",
    "health": 1200000,
    "damage": 45000,
    "cost": "Не известна.",
    "costType": "dev",
    "url": "https://i.ibb.co/QYGhtr3/Ghost-rider.jpg",
    "path": "./images/heroes/Ghost-rider.jpg",
    "available": "Да",
    "vip": false,
    "upgradeCost": 1000,
    "type": "private",
    "elements": ["legendary", "fire"],
    "blockBreeding": true
  }
}
